pyc_cleaner/__init__.py
pyc_cleaner/main.py
pyc_cleaner/pyc_logging.py
pyc_cleaner-0.0.2.dist-info/LICENSE
pyc_cleaner-0.0.2.dist-info/METADATA
pyc_cleaner-0.0.2.dist-info/WHEEL
pyc_cleaner-0.0.2.dist-info/top_level.txt
pyc_cleaner-0.0.2.dist-info/RECORD
