Metadata-Version: 2.1
Name: pyc-cleaner
Version: 0.0.2
Summary: Python cache cleaning tool
Home-page: https://github.com/whyme0/pyc_cleaner
License: UNKNOWN
Project-URL: Bug Tracker, https://github.com/whyme0/pyc_cleaner/issues
Platform: UNKNOWN
Classifier: Programming Language :: Python :: 3
Classifier: License :: OSI Approved :: MIT License
Requires-Python: >=3.7
License-File: LICENSE
